{
	"$schema": "http://schema.management.azure.com/schemas/2015-01-01/deploymentTemplate.json#",
	"contentVersion": "1.0.0.0",
	"parameters": {
		"factoryName": {
			"type": "string",
			"metadata": "Data Factory name",
			"defaultValue": "weather-forecast-adf"
		},
		"LS_Azure_KV_properties_typeProperties_baseUrl": {
			"type": "string",
			"defaultValue": "@{linkedService().KV_BaseURL}"
		},
		"LS_rest_Visual_Crossing_properties_typeProperties_url": {
			"type": "string",
			"defaultValue": "@{linkedService().BaseURL}"
		},
		"LS_AzureDataLakeStorage_properties_typeProperties_url": {
			"type": "string",
			"defaultValue": "@{linkedService().sa_url}"
		}
	},
	"variables": {
		"factoryId": "[concat('Microsoft.DataFactory/factories/', parameters('factoryName'))]"
	},
	"resources": [
		{
			"name": "[concat(parameters('factoryName'), '/LS_Azure_KV')]",
			"type": "Microsoft.DataFactory/factories/linkedServices",
			"apiVersion": "2018-06-01",
			"properties": {
				"parameters": {
					"KV_BaseURL": {
						"type": "string"
					}
				},
				"annotations": [],
				"type": "AzureKeyVault",
				"typeProperties": {
					"baseUrl": "[parameters('LS_Azure_KV_properties_typeProperties_baseUrl')]"
				}
			},
			"dependsOn": []
		},
		{
			"name": "[concat(parameters('factoryName'), '/LS_rest_Visual_Crossing')]",
			"type": "Microsoft.DataFactory/factories/linkedServices",
			"apiVersion": "2018-06-01",
			"properties": {
				"parameters": {
					"BaseURL": {
						"type": "string"
					}
				},
				"annotations": [],
				"type": "RestService",
				"typeProperties": {
					"url": "[parameters('LS_rest_Visual_Crossing_properties_typeProperties_url')]",
					"enableServerCertificateValidation": true,
					"authenticationType": "Anonymous"
				}
			},
			"dependsOn": []
		},
		{
			"name": "[concat(parameters('factoryName'), '/LS_AzureDataLakeStorage')]",
			"type": "Microsoft.DataFactory/factories/linkedServices",
			"apiVersion": "2018-06-01",
			"properties": {
				"parameters": {
					"sa_url": {
						"type": "string",
						"defaultValue": "https://weatherforecastdata.dfs.core.windows.net/"
					},
					"kv_url": {
						"type": "string",
						"defaultValue": "https://wfa-keyvault.vault.azure.net/"
					},
					"storage_secret_name": {
						"type": "string",
						"defaultValue": "weatherforecastdata-sa-key"
					}
				},
				"annotations": [],
				"type": "AzureBlobFS",
				"typeProperties": {
					"url": "[parameters('LS_AzureDataLakeStorage_properties_typeProperties_url')]",
					"accountKey": {
						"type": "AzureKeyVaultSecret",
						"store": {
							"referenceName": "LS_Azure_KV",
							"type": "LinkedServiceReference",
							"parameters": {
								"KV_BaseURL": {
									"value": "@linkedService().kv_url",
									"type": "Expression"
								}
							}
						},
						"secretName": {
							"value": "@linkedService().storage_secret_name",
							"type": "Expression"
						}
					}
				}
			},
			"dependsOn": [
				"[concat(variables('factoryId'), '/linkedServices/LS_Azure_KV')]"
			]
		}
	]
}